{"program":"({fn_1}(lam ({fn_0}(lam (push (add (connect $0)))) (next_port ({fn_0}(lam (push (add (connect $0)))) $0)))) (next_port (func ({fn_2}(lam (next_port ($0 identity))) {fn_1}(lam ({fn_0}(lam (push (add (connect $0)))) (next_port ({fn_0}(lam (push (add (connect $0)))) $0))))) ({fn_1}(lam ({fn_0}(lam (push (add (connect $0)))) (next_port ({fn_0}(lam (push (add (connect $0)))) $0)))) {fn_3}(add ({fn_2}(lam (next_port ($0 identity))) connect))))))","stitch_program":"(fn_1 (next_port (func (fn_2 fn_1) (fn_1 fn_3))))","size":7,"mass":29,"output":{"edges":[[[13,4],[14,9]],[[11,3],[12,9]],[[9,4],[14,13]],[[9,3],[12,11]],[[9,2],[10,3]],[[7,4],[8,5]],[[5,4],[8,7]],[[5,3],[6,3]],[[3,3],[6,5]],[[3,2],[10,9]],[[3,1],[4,1]],[[1,1],[4,3]],[[1,0],[2,0]],[[0,0],[2,1]]],"next_id":15,"size":8,"max_conn":10},"primary_key":[8,[1,1,1,1,2,2,3,3]],"secondary_key":[[13,[9]],[11,[9]],[9,[3,11,13]],[7,[5]],[5,[3,7]],[3,[1,5,9]],[1,[0,3]],[0,[1]]]}
